trade_engine/__init__.py
trade_engine/operations.py
trade_engine/trade_engine.py
trade_engine-1.1.4.dist-info/LICENSE
trade_engine-1.1.4.dist-info/METADATA
trade_engine-1.1.4.dist-info/WHEEL
trade_engine-1.1.4.dist-info/top_level.txt
trade_engine-1.1.4.dist-info/RECORD
