Metadata-Version: 2.1
Name: trade-engine
Version: 1.1.4
Summary: a small package for simulate trading
Home-page: https://github.com/xibalbas/trade-engine
Author: Ali moradi
Author-email: ali.mrd318@gmail.com
License: UNKNOWN
Project-URL: Bug Tracker, https://github.com/xibalbas/trade-engine/issues
Platform: UNKNOWN
Classifier: Programming Language :: Python :: 3
Classifier: License :: OSI Approved :: MIT License
Classifier: Operating System :: OS Independent
Requires-Python: >=3.7
License-File: LICENSE
Requires-Dist: pandas
